{
  "string": [
    {
      "name": "module_desc",
      "value": "音频日记应用"
    },
    {
      "name": "EntryAbility_desc",
      "value": "音频日记应用主入口"
    },
    {
      "name": "EntryAbility_label",
      "value": "音频日记"
    },
    {
      "name": "microphone_permission_reason",
      "value": "需要使用麦克风权限来录制音频日记"
    },
    {
      "name": "write_audio_permission_reason",
      "value": "需要写入音频文件权限来保存录制的音频"
    },
    {
      "name": "read_audio_permission_reason",
      "value": "需要读取音频文件权限来播放已保存的音频"
    }
  ]
}